pyAUDP/__init__.py
pyAUDP/pyAUDP.py
pyaudp-0.2.0.dist-info/LICENSE
pyaudp-0.2.0.dist-info/METADATA
pyaudp-0.2.0.dist-info/WHEEL
pyaudp-0.2.0.dist-info/top_level.txt
pyaudp-0.2.0.dist-info/RECORD
