Metadata-Version: 2.2
Name: pyAUDP
Version: 0.2.0
Summary: A pure Python asynchronous UDP module
Author-email: Wiktor Szewczyk <szewczykwikp@gmail.com>
Maintainer-email: Wiktor Szewczyk <szewczykwikp@gmail.com>
License:                                  Apache License
Project-URL: repository, https://github.com/SzewczykW/pyAUDP
Classifier: License :: OSI Approved :: Apache Software License
Classifier: Natural Language :: English
Classifier: Operating System :: POSIX :: Linux
Classifier: Operating System :: Unix
Classifier: Programming Language :: Python :: 3
Classifier: Programming Language :: Python :: 3.13
Classifier: Programming Language :: Python :: Implementation :: CPython
Classifier: Topic :: System :: Networking
Requires-Python: >=3.13
License-File: LICENSE
